bin/__init__.py
bin/main.py
autopush-0.1.1.dist-info/METADATA
autopush-0.1.1.dist-info/WHEEL
autopush-0.1.1.dist-info/entry_points.txt
autopush-0.1.1.dist-info/top_level.txt
autopush-0.1.1.dist-info/RECORD
