Metadata-Version: 2.1
Name: autopush
Version: 0.1.1
Summary: autopush cli tool allows to run git commands more simply
Home-page: https://github.com/w3cdpass/autopush
Author: w3cdpass
Author-email: kupasva663@gmail.com
Classifier: Programming Language :: Python :: 3
Classifier: License :: OSI Approved :: MIT License
Classifier: Operating System :: OS Independent
Requires-Python: >=3.7
Requires-Dist: gitpython >=3.1.31
Requires-Dist: rich >=13.3.5
Requires-Dist: InquirerPy >=0.3.4
